{
    "status": "ok",
    "totalResults": 11,
    "articles": [
      {
        "source": {
          "id": "fox-news",
          "name": "Fox News"
        },
        "author": "Fox News",
        "title": "Me Too and BLM had great reasons to start, but they went too far: Portnoy",
        "description": "Founder and president of Barstool Sports Dave Portnoy weighs in on wokeness in America by saying people are 'sick of it' on 'One Nation with Brian Kilmeade.'",
        "url": "https://video.foxnews.com/v/6307307383112/",
        "urlToImage": "https://cf-images.us-east-1.prod.boltdns.net/v1/static/694940094001/ab6ce83a-e520-44ba-98c2-1d580a095b97/ffcdd5af-7544-4df8-9bce-5e1361cfd371/1280x720/match/image.jpg",
        "publishedAt": "2022-06-05T02:07:21.7164927Z",
        "content": null
      },
      {
        "source": {
          "id": "bleacher-report",
          "name": "Bleacher Report"
        },
        "author": null,
        "title": "Smith’s Unreal Windmill Save ",
        "description": "Fan easier, fan faster and fan better with Bleacher Report. Keep up with the latest storylines, expert analysis, highlights and scores for all your favorite sports.",
        "url": "https://bleacherreport.com/videos/244732-smith-huge-save",
        "urlToImage": null,
        "publishedAt": "2022-06-05T02:07:20.7624591Z",
        "content": null
      },
      {
        "source": {
          "id": "fox-news",
          "name": "Fox News"
        },
        "author": "Fox News",
        "title": "Legendary Duke basketball coach Mike Krzyzewski goes after politicians for inaction following Uvalde tragedy",
        "description": "Former Duke basketball coach Mike Krzyzewski became the latest member of the sports world to call on politicians to act following the elementary school shooting in Uvalde, Texas.",
        "url": "https://www.foxnews.com/sports/duke-mike-krzyzewski-politicians-inaction-uvalde-tragedy",
        "urlToImage": "https://static.foxnews.com/foxnews.com/content/uploads/2022/06/GettyImages-1392655494.jpg",
        "publishedAt": "2022-06-05T00:52:18.6529933Z",
        "content": "Former Duke basketball coach Mike Krzyzewski\r\n has joined a growing number of sports figures to speak out following the elementary school shooting in Uvalde, Texas, that left 19 students and two teac… [+3327 chars]"
      },
      {
        "source": {
          "id": "lequipe",
          "name": "L'equipe"
        },
        "author": "L'EQUIPE",
        "title": "Le flash sports du 5 juin",
        "description": "Retrouvez toute l'actualité sportive dans votre flash quotidien.",
        "url": "https://www.lequipe.fr/Tous-sports/Actualites/Le-flash-sports-du-5-juin/1337000",
        "urlToImage": "https://medias.lequipe.fr/img-photo-jpg/le-flash-sports-l-equipe/1500000001649606/0:0,1997:1331-640-427-75/3fa17.jpg",
        "publishedAt": "2022-06-04T22:14:00+00:00",
        "content": "Iga Swiatek remporte facilement son 2e titre à Roland-Garros face à la jeune Américaine Coco Gauff. L'Italie et l'Allemagne ne parviennent pas à se départager (1-1) pour leur premier match de Ligue d… [+252 chars]"
      },
      {
        "source": {
          "id": "the-verge",
          "name": "The Verge"
        },
        "author": "Antonio G. Di Benedetto",
        "title": "Google’s Nest devices are up to $80 off today for Verge readers",
        "description": "Google’s wired and battery-powered video doorbells are discounted at Wellbots. You can also currently save on a smart floodlight, Google Nest Wifi Routers, iPhone cases, and the recently-released Nintendo Switch Sports.",
        "url": "https://www.theverge.com/good-deals/2022/6/4/23153336/google-nest-doorbell-wired-battery-cam-floodlight-nintendo-switch-sports-deal-sale",
        "urlToImage": "https://cdn.vox-cdn.com/thumbor/8UXSk_tD0Y2e_TrT-egivGoqAFw=/0x146:2040x1214/fit-in/1200x630/cdn.vox-cdn.com/uploads/chorus_asset/file/23267911/jtuohy_220222_5043_0005.jpg",
        "publishedAt": "2022-06-04T13:00:00Z",
        "content": "You can also save on Nintendo Switch games, iPhone cases, and budget-friendly earbuds\r\nIf you buy something from a Verge link, Vox Media may earn a commission. See our ethics statement.\r\nGoogles Nest… [+6833 chars]"
      },
      {
        "source": {
          "id": "ign",
          "name": "IGN"
        },
        "author": "Casey DeFreitas",
        "title": "Pokemon Scarlet and Violet Trailers Seem to Hint at New Gym Theme - IGN",
        "description": "Pokemon Scarlet and Violet's new trailer is filled with hints for a new theme on the horizon. Could motorsports tie-in to the new gyms?",
        "url": "https://www.ign.com/articles/pokemon-scarlet-violet-legendary-gym-motorsports",
        "urlToImage": "https://assets-prd.ignimgs.com/2022/06/03/pokemon-sv-legendary-koraidon-1654279309192.png?width=1280",
        "publishedAt": "2022-06-03T19:04:07Z",
        "content": "Pokemon Scarlet and Violet's second trailer revealed new Pokemon, locations, and people but more notably hints at a potential gym theme. What if Pokemon Scarlet and Violet's gyms are themed after For… [+6621 chars]"
      },
      {
        "source": {
          "id": "the-washington-times",
          "name": "The Washington Times"
        },
        "author": "The Washington Times https://www.washingtontimes.com",
        "title": "Special Section: District of Sports Podcast",
        "description": "Washington Times sports reporters Matthew Paras, Jacob Calvin Meyer, and George Gerbo get together bi-weekly for a discussion on the latest storylines, details, and trends in the world of D.C. sports.",
        "url": "https://www.washingtontimes.com/specials/district-sports-podcast/",
        "urlToImage": "https://media.washtimes.com/media/specials/thumbnails/DOSthumbnailV2.jpg",
        "publishedAt": "2022-06-02T20:37:30.1795109Z",
        "content": "Washington Times sports reporters Matthew Paras, Jacob Calvin Meyer, and George Gerbo get together bi-weekly for a discussion on the latest storylines, details, and trends in the world of D.C. sports… [+1484 chars]"
      },
      {
        "source": {
          "id": "bleacher-report",
          "name": "Bleacher Report"
        },
        "author": null,
        "title": "Shaq Interview with Taylor Rooks ",
        "description": "Fan easier, fan faster and fan better with Bleacher Report. Keep up with the latest storylines, expert analysis, highlights and scores for all your favorite sports.",
        "url": "https://bleacherreport.com/videos/243254-taylor-rooks-x-shaq-vodcast",
        "urlToImage": null,
        "publishedAt": "2022-05-24T16:37:46.0357309Z",
        "content": null
      },
      {
        "source": {
          "id": "bleacher-report",
          "name": "Bleacher Report"
        },
        "author": null,
        "title": " &#x27;The Champions&#x27; Episode 2 ",
        "description": "Fan easier, fan faster and fan better with Bleacher Report. Keep up with the latest storylines, expert analysis, highlights and scores for all your favorite sports.",
        "url": "https://bleacherreport.com/videos/243733-the-champions-season-6-episode-2",
        "urlToImage": null,
        "publishedAt": "2022-05-24T16:37:41.5524723Z",
        "content": null
      },
      {
        "source": {
          "id": "usa-today",
          "name": "USA Today"
        },
        "author": null,
        "title": "Daily Briefing",
        "description": "The day's top stories, from sports to movies to politics to world events.",
        "url": "https://profile.usatoday.com/newsletters/daily-briefing/",
        "urlToImage": "https://profile.usatoday.com/newsletters/resources/usat/property/usatoday/newsletter-thumbs/8872UT-E-NLETTER02@2x.jpg",
        "publishedAt": "2021-08-15T15:35:07+00:00",
        "content": "The day's top stories, from sports to movies to politics to world events."
      },
      {
        "source": {
          "id": "the-washington-times",
          "name": "The Washington Times"
        },
        "author": "The Washington Times http://www.washingtontimes.com",
        "title": "Latest Quizzes",
        "description": "Take a break from the hard news of the day and enjoy a quiz on entertainment, sports, history and politics only from The Washington Times.",
        "url": "https://www.washingtontimes.com/quiz/",
        "urlToImage": null,
        "publishedAt": "2021-02-10T03:52:37.2719772Z",
        "content": "Featured Quizzes\r\nAttention all William Shakespeare experts. Pinpoint the prose's origin plucked from one of his many famous plays in this multiple-choice challenge.\r\n Shares \r\nName these legendary c… [+32652 chars]"
      }
    ]
  }